stream_chat_python_cli/__init__.py
stream_chat_python_cli/cli.py
stream_chat_python_cli-0.0.2.dist-info/METADATA
stream_chat_python_cli-0.0.2.dist-info/WHEEL
stream_chat_python_cli-0.0.2.dist-info/entry_points.txt
stream_chat_python_cli-0.0.2.dist-info/top_level.txt
stream_chat_python_cli-0.0.2.dist-info/RECORD
