Metadata-Version: 2.1
Name: stream-chat-python-cli
Version: 0.0.2
Summary: CLI for Stream Chat
Home-page: http://github.com/GetStream/stream-chat-python-cli
Author: Nick Parsons
Author-email: nick@getstream.io
License: UNKNOWN
Platform: UNKNOWN
Classifier: Intended Audience :: Developers
Classifier: Intended Audience :: System Administrators
Classifier: Operating System :: OS Independent
Classifier: Topic :: Software Development
Classifier: Development Status :: 5 - Production/Stable
Classifier: Natural Language :: English
Classifier: Programming Language :: Python :: 3
Classifier: Programming Language :: Python :: 3.4
Classifier: Programming Language :: Python :: 3.5
Classifier: Programming Language :: Python :: 3.6
Classifier: Programming Language :: Python :: 3.7
Classifier: Topic :: Software Development :: Libraries :: Python Modules
Requires-Dist: certifi (==2019.3.9)
Requires-Dist: chardet (==3.0.4)
Requires-Dist: Click (==7.0)
Requires-Dist: idna (==2.8)
Requires-Dist: pycryptodomex (==3.4.7)
Requires-Dist: PyJWT (==1.7.1)
Requires-Dist: requests (==2.21.0)
Requires-Dist: six (==1.12.0)
Requires-Dist: stream-chat (==0.2.0)
Requires-Dist: urllib3 (==1.24.2)
Requires-Dist: uuid (==1.30)
